Id/__init__.py
Id/san.py
image_downloader_san-0.1.0.dist-info/LICENSE
image_downloader_san-0.1.0.dist-info/METADATA
image_downloader_san-0.1.0.dist-info/WHEEL
image_downloader_san-0.1.0.dist-info/top_level.txt
image_downloader_san-0.1.0.dist-info/RECORD
