Metadata-Version: 2.1
Name: image-downloader-san
Version: 0.1.0
Summary: An image downloader
Home-page: https://github.com/TaprisSugarbell/Image-downloader-san
Author: Sayu Ogiwara
Author-email: anonesayu@gmail.com
License: MIT
Platform: UNKNOWN
Classifier: Programming Language :: Python :: 3
Classifier: License :: OSI Approved :: MIT License
Classifier: Operating System :: OS Independent
Requires-Dist: requests
Requires-Dist: beautifulsoup4
Requires-Dist: html-to-json
